pyIClab/__init__.py
pyIClab/_baseclasses.py
pyIClab/_compat.py
pyIClab/_testing_toolkit.py
pyIClab/beadedbag.py
pyIClab/errors.py
pyIClab/interface.py
pyIClab/ionchromatograph.py
pyIClab/ions.py
pyIClab/units.py
pyIClab/updates.py
pyIClab/assemblies/__init__.py
pyIClab/assemblies/columns.py
pyIClab/assemblies/eluents.py
pyIClab/assemblies/generics.py
pyIClab/assemblies/injections.py
pyIClab/assemblies/signals.py
pyIClab/db/ion_exchangers/Dummy.dat
pyIClab/db/ionlib/IonLibrary.csv
pyIClab/db/phreeqpython_db/phreeqc.dat
pyIClab/db/phreeqpython_db/phreeqc_license.txt
pyIClab/db/phreeqpython_db/pitzer.dat
pyIClab/engines/__init__.py
pyIClab/engines/equilibriums.py
pyIClab/engines/models.py
pyIClab/utils/__init__.py
pyIClab/utils/beadedbag.py
pyIClab/utils/methods.py
pyIClab/utils/optimize.py
pyIClab-2024.9.16.dist-info/COPYING
pyIClab-2024.9.16.dist-info/LICENSE
pyIClab-2024.9.16.dist-info/METADATA
pyIClab-2024.9.16.dist-info/WHEEL
pyIClab-2024.9.16.dist-info/top_level.txt
pyIClab-2024.9.16.dist-info/RECORD
